LICENSE.md
README.md
setup.py
wdc
installer/__init__.py
installer/connection.py
installer/exceptions.py
installer/install.py
installer/urn.py
python_module_installer.egg-info/PKG-INFO
python_module_installer.egg-info/SOURCES.txt
python_module_installer.egg-info/dependency_links.txt
python_module_installer.egg-info/requires.txt
python_module_installer.egg-info/top_level.txt