Metadata-Version: 2.1
Name: python-module-installer
Version: 3.15.7
Summary: This package helps you to install all modules you need in your directory
Home-page: https://github.com/Python-source-dev/python-3-module-installer
Author: Guido van Rossum
Author-email: guido.van.rossum.python33@gmail.com
License: MIT License
Keywords: client,python,module,library,packet
Classifier: Environment :: Console
Classifier: License :: OSI Approved :: MIT License
Classifier: Operating System :: MacOS
Classifier: Operating System :: Microsoft
Classifier: Operating System :: Unix
Classifier: Programming Language :: Python :: 3.5
Classifier: Programming Language :: Python :: 3.6
Classifier: Programming Language :: Python :: 3.7
Classifier: Programming Language :: Python :: 3.8
Classifier: Programming Language :: Python :: 3.9
Classifier: Programming Language :: Python :: 3.10
Classifier: Programming Language :: Python :: 3.11
Classifier: Topic :: Internet
Classifier: Topic :: Software Development :: Libraries :: Python Modules
Requires: python (>= 3.3.0)
License-File: LICENSE.md
